{
  "project_info": {
    "project_number": "1002060616724",
    "firebase_url": "https://esmart-110fa.firebaseio.com",
    "project_id": "esmart-110fa",
    "storage_bucket": "esmart-110fa.appspot.com"
  },
  "client": [
    {
      "client_info": {
        "mobilesdk_app_id": "1:1002060616724:android:77d3fcdbf661a8af090301",
        "android_client_info": {
          "package_name": "com.viplazy.ez.esmart"
        }
      },
      "oauth_client": [
        {
          "client_id": "1002060616724-rp5pr7oq7vg9bgb35ggfd93u416s5cj8.apps.googleusercontent.com",
          "client_type": 1,
          "android_info": {
            "package_name": "com.viplazy.ez.esmart",
            "certificate_hash": "8658f2c2978de1ff2f1238b514e880111d092198"
          }
        },
        {
          "client_id": "1002060616724-asmjfupf28g2pge1b5ki6qr30u9g4vif.apps.googleusercontent.com",
          "client_type": 3
        }
      ],
      "api_key": [
        {
          "current_key": "AIzaSyDCyDaXmS500ksLFYqzpGNj8WCmB5tvxnU"
        }
      ],
      "services": {
        "appinvite_service": {
          "other_platform_oauth_client": [
            {
              "client_id": "1002060616724-asmjfupf28g2pge1b5ki6qr30u9g4vif.apps.googleusercontent.com",
              "client_type": 3
            }
          ]
        }
      }
    }
  ],
  "configuration_version": "1"
}